LICENSE
README.md
setup.py
vads/__init__.py
vads/base.py
vads.egg-info/PKG-INFO
vads.egg-info/SOURCES.txt
vads.egg-info/dependency_links.txt
vads.egg-info/requires.txt
vads.egg-info/top_level.txt